CHANGELOG.txt
LICENCE.txt
MANIFEST.in
README.md
commands.txt
run.py
setup.py
traceUts/__init__.py
traceUts.egg-info/PKG-INFO
traceUts.egg-info/SOURCES.txt
traceUts.egg-info/dependency_links.txt
traceUts.egg-info/top_level.txt